AUTHORS.txt
CHANGES.txt
LICENSE.txt
MANIFEST.in
README.rst
requirements.txt
setup.py
version.txt
vac_templater/__init__.py
vac_templater/assets_mapping.py
vac_templater/context_processors.py
vac_templater/middleware.py
vac_templater/runner.py
vac_templater/settings.py
vac_templater/signals.py
vac_templater/urls.py
vac_templater/uwsgi.py
vac_templater/wsgi.py
vac_templater.egg-info/PKG-INFO
vac_templater.egg-info/SOURCES.txt
vac_templater.egg-info/dependency_links.txt
vac_templater.egg-info/entry_points.txt
vac_templater.egg-info/requires.txt
vac_templater.egg-info/top_level.txt
vac_templater/assets/default-bootstrap--en-a07d3c43e62a0757a89dd2a6f554161f7f943404.js
vac_templater/assets/default-bundle--en-9b7c64a84edd2ad3ae304506e8cda9260dd4f54d.js
vac_templater/assets/default-bundle-c3ac065b1db3b5f2734740b8b440330ae101078d.css
vac_templater/assets/favicon-908651f9d78cd5064750219a970d26d546172109.ico
vac_templater/assets/vac-templater/default/fonts/Ubuntu-Medium-webfont-19bef830aba0fca66525a6c3fb19033e558fd566.woff
vac_templater/assets/vac-templater/default/fonts/Ubuntu-Medium-webfont-5e59848a163fb8a4a8a38379a1615a1ae035640f.ttf
vac_templater/assets/vac-templater/default/fonts/Ubuntu-Medium-webfont-72cd431c64c6df1b2a7f664d53416a58f58eb7f3.eot
vac_templater/assets/vac-templater/default/fonts/Ubuntu-Medium-webfont-fe9ebe1bb06e9e2add26ecd9687554320eac0262.svg
vac_templater/assets/vac-templater/default/fonts/Ubuntu-Regular-webfont-0cac9fe6b49948a9f4ccde332465a6db83f6b38f.ttf
vac_templater/assets/vac-templater/default/fonts/Ubuntu-Regular-webfont-4f5c8acb8065aee54659fcf7201aa50adfb842d8.woff
vac_templater/assets/vac-templater/default/fonts/Ubuntu-Regular-webfont-5936977660e6aa4f5df80b4afec7d0b36632492c.eot
vac_templater/assets/vac-templater/default/fonts/Ubuntu-Regular-webfont-bb74d56f4899de902002033f1cadf08346a9ae3c.svg
vac_templater/assets/vac-templater/default/fonts/plugins/bootstrap/glyphicons-halflings-regular-278e49a86e634da6f2a02f3b47dd9d2a8f26210f.woff
vac_templater/assets/vac-templater/default/fonts/plugins/bootstrap/glyphicons-halflings-regular-44bc1850f570972267b169ae18f1cb06b611ffa2.ttf
