Metadata-Version: 1.1
Name: vac-templater
Version: 0.3
Summary: VAC Templater.
Home-page: https://www.allenta.com
Author: Allenta Consulting S.L.
Author-email: info@allenta.com
License: GPL
Platform: UNKNOWN
Classifier: Framework :: Django
Classifier: Intended Audience :: Developers
Classifier: Intended Audience :: System Administrators
Classifier: Operating System :: OS Independent
